datashuttle/__init__.py
datashuttle/datashuttle_class.py
datashuttle/datashuttle_functions.py
datashuttle/tui_launcher.py
datashuttle/configs/__init__.py
datashuttle/configs/canonical_configs.py
datashuttle/configs/canonical_folders.py
datashuttle/configs/canonical_tags.py
datashuttle/configs/config_class.py
datashuttle/configs/links.py
datashuttle/configs/load_configs.py
datashuttle/tui/app.py
datashuttle/tui/custom_widgets.py
datashuttle/tui/interface.py
datashuttle/tui/tooltips.py
datashuttle/tui/css/tui_menu.tcss
datashuttle/tui/css/tui_style.tcss
datashuttle/tui/css/tui_tab.tcss
datashuttle/tui/screens/create_folder_settings.py
datashuttle/tui/screens/datatypes.py
datashuttle/tui/screens/get_help.py
datashuttle/tui/screens/modal_dialogs.py
datashuttle/tui/screens/new_project.py
datashuttle/tui/screens/project_manager.py
datashuttle/tui/screens/project_selector.py
datashuttle/tui/screens/settings.py
datashuttle/tui/screens/setup_ssh.py
datashuttle/tui/screens/validate_at_path.py
datashuttle/tui/shared/configs_content.py
datashuttle/tui/shared/validate_content.py
datashuttle/tui/tabs/create_folders.py
datashuttle/tui/tabs/logging.py
datashuttle/tui/tabs/transfer.py
datashuttle/tui/tabs/transfer_status_tree.py
datashuttle/tui/utils/tui_decorators.py
datashuttle/tui/utils/tui_validators.py
datashuttle/utils/__init__.py
datashuttle/utils/custom_exceptions.py
datashuttle/utils/custom_types.py
datashuttle/utils/data_transfer.py
datashuttle/utils/decorators.py
datashuttle/utils/ds_logger.py
datashuttle/utils/folder_class.py
datashuttle/utils/folders.py
datashuttle/utils/formatting.py
datashuttle/utils/getters.py
datashuttle/utils/rclone.py
datashuttle/utils/ssh.py
datashuttle/utils/utils.py
datashuttle/utils/validation.py
datashuttle-0.7.1.dist-info/licenses/LICENSE
datashuttle-0.7.1.dist-info/METADATA
datashuttle-0.7.1.dist-info/WHEEL
datashuttle-0.7.1.dist-info/entry_points.txt
datashuttle-0.7.1.dist-info/top_level.txt
datashuttle-0.7.1.dist-info/RECORD
